odoo/addons/website_sale_product_detail_attribute_image/README.rst
odoo/addons/website_sale_product_detail_attribute_image/__init__.py
odoo/addons/website_sale_product_detail_attribute_image/__manifest__.py
odoo/addons/website_sale_product_detail_attribute_image/controllers/__init__.py
odoo/addons/website_sale_product_detail_attribute_image/controllers/main.py
odoo/addons/website_sale_product_detail_attribute_image/i18n/es.po
odoo/addons/website_sale_product_detail_attribute_image/i18n/es_AR.po
odoo/addons/website_sale_product_detail_attribute_image/i18n/it.po
odoo/addons/website_sale_product_detail_attribute_image/i18n/nl.po
odoo/addons/website_sale_product_detail_attribute_image/i18n/pt.po
odoo/addons/website_sale_product_detail_attribute_image/i18n/pt_BR.po
odoo/addons/website_sale_product_detail_attribute_image/i18n/website_sale_product_detail_attribute_image.pot
odoo/addons/website_sale_product_detail_attribute_image/models/__init__.py
odoo/addons/website_sale_product_detail_attribute_image/models/product_attribute.py
odoo/addons/website_sale_product_detail_attribute_image/readme/CONTRIBUTORS.md
odoo/addons/website_sale_product_detail_attribute_image/readme/CREDITS.md
odoo/addons/website_sale_product_detail_attribute_image/readme/DESCRIPTION.md
odoo/addons/website_sale_product_detail_attribute_image/readme/USAGE.md
odoo/addons/website_sale_product_detail_attribute_image/static/description/icon.png
odoo/addons/website_sale_product_detail_attribute_image/static/description/index.html
odoo/addons/website_sale_product_detail_attribute_image/static/src/img/EN374.png
odoo/addons/website_sale_product_detail_attribute_image/static/src/img/EN374_2003.png
odoo/addons/website_sale_product_detail_attribute_image/static/src/img/EN388.png
odoo/addons/website_sale_product_detail_attribute_image/static/src/scss/style.scss
odoo/addons/website_sale_product_detail_attribute_image/static/tests/tours/website_sale_product_detail_attribute_image.esm.js
odoo_addon_website_sale_product_detail_attribute_image-18.0.1.0.0.3.dist-info/METADATA
odoo_addon_website_sale_product_detail_attribute_image-18.0.1.0.0.3.dist-info/WHEEL
odoo_addon_website_sale_product_detail_attribute_image-18.0.1.0.0.3.dist-info/top_level.txt
odoo_addon_website_sale_product_detail_attribute_image-18.0.1.0.0.3.dist-info/RECORD
